mailgrab/__init__.py
mailgrab/__version__.py
mailgrab/exceptions.py
mailgrab/mailgrab.py
mailgrab-1.3.0.dist-info/licenses/LICENSE
mailgrab-1.3.0.dist-info/METADATA
mailgrab-1.3.0.dist-info/WHEEL
mailgrab-1.3.0.dist-info/entry_points.txt
mailgrab-1.3.0.dist-info/top_level.txt
mailgrab-1.3.0.dist-info/RECORD
