Metadata-Version: 2.4
Name: mailgrab
Version: 1.3.0
Summary: Un outil Python pour extraire des adresses email depuis des pages web ou des fichiers texte.
Home-page: https://github.com/nanaelie/mailgrab
Author: nae.devp
Author-email: nae.devp@gmail.com
Classifier: Programming Language :: Python :: 3
Classifier: Operating System :: OS Independent
Classifier: License :: OSI Approved :: MIT License
Classifier: Topic :: Utilities
Classifier: Topic :: Internet :: WWW/HTTP :: Indexing/Search
Requires-Python: >=3.7
License-File: LICENSE
Requires-Dist: playwright>=1.44.0
Dynamic: author
Dynamic: author-email
Dynamic: classifier
Dynamic: description
Dynamic: description-content-type
Dynamic: home-page
Dynamic: license-file
Dynamic: requires-dist
Dynamic: requires-python
Dynamic: summary
